utter_more/__init__.py
utter_more/utter_more.py
utter_more-1.0.1.dist-info/METADATA
utter_more-1.0.1.dist-info/RECORD
utter_more-1.0.1.dist-info/WHEEL
utter_more-1.0.1.dist-info/top_level.txt
