Metadata-Version: 2.1
Name: utter-more
Version: 1.0.1
Summary: Creates utterances for Amazon's Alexa.
Home-page: https://github.com/crumpstrr33/Utter-More
Author: Jacob Scott
Author-email: jscott12009@gmail.com
License: MIT
Platform: UNKNOWN
Classifier: Intended Audience :: Developers
Classifier: License :: OSI Approved :: MIT License
Classifier: Programming Language :: Python :: 3 :: Only
Requires-Python: >=3
